transport_dependency/__init__.py
transport_dependency/independence_test.py
transport_dependency/other_coeffs.py
transport_dependency/td_functions.py
transport_dependency-0.0.1.dist-info/LICENCE
transport_dependency-0.0.1.dist-info/METADATA
transport_dependency-0.0.1.dist-info/WHEEL
transport_dependency-0.0.1.dist-info/top_level.txt
transport_dependency-0.0.1.dist-info/RECORD
