Metadata-Version: 2.1
Name: transport-dependency
Version: 0.0.1
Summary: A package to compute optimal transport based dependency measures such as the transport correlation
Home-page: UNKNOWN
Author: Thomas Giacomo Nies
Author-email: thomas.nies@uni-goettingen.de
License: MIT
Platform: UNKNOWN
License-File: LICENCE
Requires-Dist: numpy
Requires-Dist: scipy
Requires-Dist: pot
